connect4_robot_j4/LICENSE
connect4_robot_j4/README.md
connect4_robot_j4/__init__.py
connect4_robot_j4/constants.py
connect4_robot_j4/core.py
connect4_robot_j4/game_data.py
connect4_robot_j4/game_loop.py
connect4_robot_j4/game_state.py
connect4_robot_j4/main.py
connect4_robot_j4/play.bat
connect4_robot_j4/arduino_serial/__init__.py
connect4_robot_j4/arduino_serial/arduino_connection.py
connect4_robot_j4/arduino_serial/serial_connection.py
connect4_robot_j4/camera/__init__.py
connect4_robot_j4/camera/camera.py
connect4_robot_j4/camera/camera_handler.py
connect4_robot_j4/firebase_db/__init__.py
connect4_robot_j4/firebase_db/firebase.py
connect4_robot_j4/minimax/__init__.py
connect4_robot_j4/minimax/minimax_functions.py
connect4_robot_j4-1.0.1.dist-info/METADATA
connect4_robot_j4-1.0.1.dist-info/WHEEL
connect4_robot_j4-1.0.1.dist-info/entry_points.txt
connect4_robot_j4-1.0.1.dist-info/top_level.txt
connect4_robot_j4-1.0.1.dist-info/RECORD
