Metadata-Version: 2.4
Name: connect4-robot-j4
Version: 1.0.1
Summary: Un Puissance 4 robotisé avec vision par ordinateur, IA et Arduino
Author: Vaucanson Robot J4 Team
Requires-Python: >=3.8
Requires-Dist: opencv-python>=4.5
Requires-Dist: pygame>=2.0
Requires-Dist: pyserial>=3.5
Requires-Dist: numpy>=1.21
Requires-Dist: firebase-admin>=6.9.0
